{
  "slug": "nullité-de-la-poursuite",
  "sourcePath": "/post/nullité-de-la-poursuite",
  "capturedAt": "2026-07-17",
  "ricos": {
    "nodes": [
      {
        "type": "PARAGRAPH",
        "id": "26mvhj5hbw",
        "nodes": [
          {
            "type": "TEXT",
            "id": "",
            "nodes": [],
            "textData": {
              "text": "Bordeaux, 8 septembre 2025.",
              "decorations": [
                {
                  "type": "BOLD"
                }
              ]
            }
          },
          {
            "type": "TEXT",
            "id": "",
            "nodes": [],
            "textData": {
              "text": " Le Tribunal correctionnel de Bordeaux a fait droit à l'exception de nullité de la poursuite soulevée ",
              "decorations": []
            }
          },
          {
            "type": "TEXT",
            "id": "",
            "nodes": [],
            "textData": {
              "text": "in limine litis",
              "decorations": [
                {
                  "type": "ITALIC"
                }
              ]
            }
          },
          {
            "type": "TEXT",
            "id": "",
            "nodes": [],
            "textData": {
              "text": " par notre cabinet pour Mme T., gérante d'une auto-école bordelaise. La ",
              "decorations": []
            }
          },
          {
            "type": "TEXT",
            "id": "",
            "nodes": [],
            "textData": {
              "text": "convocation par officier de police judiciaire (COPJ)",
              "decorations": [
                {
                  "type": "BOLD"
                }
              ]
            }
          },
          {
            "type": "TEXT",
            "id": "",
            "nodes": [],
            "textData": {
              "text": " est ",
              "decorations": []
            }
          },
          {
            "type": "TEXT",
            "id": "",
            "nodes": [],
            "textData": {
              "text": "annulée",
              "decorations": [
                {
                  "type": "BOLD"
                }
              ]
            }
          },
          {
            "type": "TEXT",
            "id": "",
            "nodes": [],
            "textData": {
              "text": " et le ministère public est ",
              "decorations": []
            }
          },
          {
            "type": "TEXT",
            "id": "",
            "nodes": [],
            "textData": {
              "text": "renvoyé à mieux se pourvoir",
              "decorations": [
                {
                  "type": "BOLD"
                }
              ]
            }
          },
          {
            "type": "TEXT",
            "id": "",
            "nodes": [],
            "textData": {
              "text": ". Cette décision n'est pas un jugement au fond sur la culpabilité : c'est le contrôle de la régularité de l'acte saisissant le tribunal. Pour comprendre les différents statuts en procédure pénale : ",
              "decorations": []
            }
          },
          {
            "type": "TEXT",
            "id": "",
            "nodes": [],
            "textData": {
              "text": "Mis en cause, témoin assisté, mis en examen, prévenu ou accusé : quelles différences ?",
              "decorations": [
                {
                  "type": "LINK",
                  "linkData": {
                    "link": {
                      "url": "https://www.jplouton-avocat.fr/post/mis-en-cause-temoin-assiste-prevenu-accuse-differences",
                      "target": "SELF",
                      "rel": {
                        "nofollow": false,
                        "sponsored": false,
                        "ugc": false
                      }
                    }
                  }
                },
                {
                  "type": "UNDERLINE",
                  "underlineData": true
                }
              ]
            }
          },
          {
            "type": "TEXT",
            "id": "",
            "nodes": [],
            "textData": {
              "text": ".",
              "decorations": []
            }
          }
        ],
        "paragraphData": {}
      },
      {
        "type": "PARAGRAPH",
        "id": "p8cyei9zta",
        "nodes": [
          {
            "type": "TEXT",
            "id": "",
            "nodes": [],
            "textData": {
              "text": " ",
              "decorations": []
            }
          }
        ],
        "paragraphData": {}
      },
      {
        "type": "HEADING",
        "id": "szyenssxa",
        "nodes": [
          {
            "type": "TEXT",
            "id": "",
            "nodes": [],
            "textData": {
              "text": "Contexte : enquête sur de faux permis de conduire en Gironde",
              "decorations": []
            }
          }
        ],
        "headingData": {
          "level": 2.0
        }
      },
      {
        "type": "PARAGRAPH",
        "id": "fuddqqnljw",
        "nodes": [
          {
            "type": "TEXT",
            "id": "",
            "nodes": [],
            "textData": {
              "text": "Au printemps 2022, l'administration signale des ",
              "decorations": []
            }
          },
          {
            "type": "TEXT",
            "id": "",
            "nodes": [],
            "textData": {
              "text": "anomalies de réussite à l'épreuve pratique",
              "decorations": [
                {
                  "type": "BOLD"
                }
              ]
            }
          },
          {
            "type": "TEXT",
            "id": "",
            "nodes": [],
            "textData": {
              "text": " du permis de conduire. Une enquête préliminaire est ouverte : réquisitions, surveillances, exploitation de comptes bancaires.",
              "decorations": []
            }
          }
        ],
        "paragraphData": {}
      },
      {
        "type": "PARAGRAPH",
        "id": "7tszhykchq",
        "nodes": [
          {
            "type": "TEXT",
            "id": "",
            "nodes": [],
            "textData": {
              "text": " ",
              "decorations": []
            }
          }
        ],
        "paragraphData": {}
      },
      {
        "type": "PARAGRAPH",
        "id": "ol6dviifq",
        "nodes": [
          {
            "type": "TEXT",
            "id": "",
            "nodes": [],
            "textData": {
              "text": "Les actes d'enquête évoquent :",
              "decorations": []
            }
          }
        ],
        "paragraphData": {}
      },
      {
        "type": "PARAGRAPH",
        "id": "xvo7s058ig",
        "nodes": [
          {
            "type": "TEXT",
            "id": "",
            "nodes": [],
            "textData": {
              "text": " ",
              "decorations": []
            }
          }
        ],
        "paragraphData": {}
      },
      {
        "type": "BULLETED_LIST",
        "id": "zzgkxtodnw",
        "nodes": [
          {
            "type": "LIST_ITEM",
            "id": "j7pawdbvyg",
            "nodes": [
              {
                "type": "PARAGRAPH",
                "id": "7h4z2p0dbq",
                "nodes": [
                  {
                    "type": "TEXT",
                    "id": "",
                    "nodes": [],
                    "textData": {
                      "text": "des ",
                      "decorations": []
                    }
                  },
                  {
                    "type": "TEXT",
                    "id": "",
                    "nodes": [],
                    "textData": {
                      "text": "contacts extra-professionnels",
                      "decorations": [
                        {
                          "type": "BOLD"
                        }
                      ]
                    }
                  },
                  {
                    "type": "TEXT",
                    "id": "",
                    "nodes": [],
                    "textData": {
                      "text": " entre une responsable d'auto-école et un examinateur ;",
                      "decorations": []
                    }
                  }
                ],
                "paragraphData": {}
              }
            ]
          },
          {
            "type": "LIST_ITEM",
            "id": "s0mu0o4sag",
            "nodes": [
              {
                "type": "PARAGRAPH",
                "id": "lrxyycisa",
                "nodes": [
                  {
                    "type": "TEXT",
                    "id": "",
                    "nodes": [],
                    "textData": {
                      "text": "des ",
                      "decorations": []
                    }
                  },
                  {
                    "type": "TEXT",
                    "id": "",
                    "nodes": [],
                    "textData": {
                      "text": "remises d'espèces",
                      "decorations": [
                        {
                          "type": "BOLD"
                        }
                      ]
                    }
                  },
                  {
                    "type": "TEXT",
                    "id": "",
                    "nodes": [],
                    "textData": {
                      "text": " supposées à l'issue d'épreuves ;",
                      "decorations": []
                    }
                  }
                ],
                "paragraphData": {}
              }
            ]
          },
          {
            "type": "LIST_ITEM",
            "id": "l9cst5oww",
            "nodes": [
              {
                "type": "PARAGRAPH",
                "id": "cggvidxqhg",
                "nodes": [
                  {
                    "type": "TEXT",
                    "id": "",
                    "nodes": [],
                    "textData": {
                      "text": "la ",
                      "decorations": []
                    }
                  },
                  {
                    "type": "TEXT",
                    "id": "",
                    "nodes": [],
                    "textData": {
                      "text": "réservation de créneaux d'examen",
                      "decorations": [
                        {
                          "type": "BOLD"
                        }
                      ]
                    }
                  },
                  {
                    "type": "TEXT",
                    "id": "",
                    "nodes": [],
                    "textData": {
                      "text": " alignés sur le planning d'un examinateur.",
                      "decorations": []
                    }
                  }
                ],
                "paragraphData": {}
              }
            ]
          }
        ],
        "bulletedListData": {
          "indentation": 0.0
        }
      },
      {
        "type": "PARAGRAPH",
        "id": "uzmeu7qzra",
        "nodes": [
          {
            "type": "TEXT",
            "id": "",
            "nodes": [],
            "textData": {
              "text": " ",
              "decorations": []
            }
          }
        ],
        "paragraphData": {}
      },
      {
        "type": "PARAGRAPH",
        "id": "073iwvpdw",
        "nodes": [
          {
            "type": "TEXT",
            "id": "",
            "nodes": [],
            "textData": {
              "text": "Plusieurs qualifications pénales ont été visées : ",
              "decorations": []
            }
          },
          {
            "type": "TEXT",
            "id": "",
            "nodes": [],
            "textData": {
              "text": "escroquerie",
              "decorations": [
                {
                  "type": "BOLD"
                }
              ]
            }
          },
          {
            "type": "TEXT",
            "id": "",
            "nodes": [],
            "textData": {
              "text": ", ",
              "decorations": []
            }
          },
          {
            "type": "TEXT",
            "id": "",
            "nodes": [],
            "textData": {
              "text": "faux et usage de faux",
              "decorations": [
                {
                  "type": "BOLD"
                }
              ]
            }
          },
          {
            "type": "TEXT",
            "id": "",
            "nodes": [],
            "textData": {
              "text": ", ",
              "decorations": []
            }
          },
          {
            "type": "TEXT",
            "id": "",
            "nodes": [],
            "textData": {
              "text": "obtention indue de document administratif",
              "decorations": [
                {
                  "type": "BOLD"
                }
              ]
            }
          },
          {
            "type": "TEXT",
            "id": "",
            "nodes": [],
            "textData": {
              "text": " et ",
              "decorations": []
            }
          },
          {
            "type": "TEXT",
            "id": "",
            "nodes": [],
            "textData": {
              "text": "blanchiment",
              "decorations": [
                {
                  "type": "BOLD"
                }
              ]
            }
          },
          {
            "type": "TEXT",
            "id": "",
            "nodes": [],
            "textData": {
              "text": ".",
              "decorations": []
            }
          }
        ],
        "paragraphData": {}
      },
      {
        "type": "PARAGRAPH",
        "id": "cpv4gcl4fw",
        "nodes": [
          {
            "type": "TEXT",
            "id": "",
            "nodes": [],
            "textData": {
              "text": " ",
              "decorations": []
            }
          }
        ],
        "paragraphData": {}
      },
      {
        "type": "PARAGRAPH",
        "id": "fhj0pjscrw",
        "nodes": [
          {
            "type": "TEXT",
            "id": "",
            "nodes": [],
            "textData": {
              "text": "Si vous êtes convoqué, entendu ou interpellé dans un dossier pénal, ces ressources vous aident à protéger immédiatement vos droits :",
              "decorations": []
            }
          }
        ],
        "paragraphData": {}
      },
      {
        "type": "PARAGRAPH",
        "id": "l0bybzyqhw",
        "nodes": [
          {
            "type": "TEXT",
            "id": "",
            "nodes": [],
            "textData": {
              "text": " ",
              "decorations": []
            }
          }
        ],
        "paragraphData": {}
      },
      {
        "type": "BULLETED_LIST",
        "id": "afzmx5nra",
        "nodes": [
          {
            "type": "LIST_ITEM",
            "id": "fwxncereq",
            "nodes": [
              {
                "type": "PARAGRAPH",
                "id": "lafdntavbq",
                "nodes": [
                  {
                    "type": "TEXT",
                    "id": "",
                    "nodes": [],
                    "textData": {
                      "text": "Garde à vue ou audition libre : différences essentielles",
                      "decorations": [
                        {
                          "type": "LINK",
                          "linkData": {
                            "link": {
                              "url": "https://www.jplouton-avocat.fr/post/garde-%C3%A0-vue-ou-audition-libre-diff%C3%A9rences-essentielles-%C3%A0-conna%C3%AEtre",
                              "target": "SELF",
                              "rel": {
                                "nofollow": false,
                                "sponsored": false,
                                "ugc": false
                              }
                            }
                          }
                        },
                        {
                          "type": "UNDERLINE",
                          "underlineData": true
                        }
                      ]
                    }
                  }
                ],
                "paragraphData": {}
              }
            ]
          },
          {
            "type": "LIST_ITEM",
            "id": "eq0mq59ww",
            "nodes": [
              {
                "type": "PARAGRAPH",
                "id": "aahl0kvzvg",
                "nodes": [
                  {
                    "type": "TEXT",
                    "id": "",
                    "nodes": [],
                    "textData": {
                      "text": "Droits en garde à vue : la liste complète",
                      "decorations": [
                        {
                          "type": "LINK",
                          "linkData": {
                            "link": {
                              "url": "https://www.jplouton-avocat.fr/post/mes-droits-en-garde-a-vue",
                              "target": "SELF",
                              "rel": {
                                "nofollow": false,
                                "sponsored": false,
                                "ugc": false
                              }
                            }
                          }
                        },
                        {
                          "type": "UNDERLINE",
                          "underlineData": true
                        }
                      ]
                    }
                  }
                ],
                "paragraphData": {}
              }
            ]
          },
          {
            "type": "LIST_ITEM",
            "id": "kqolv7dj5a",
            "nodes": [
              {
                "type": "PARAGRAPH",
                "id": "7k3b56tnca",
                "nodes": [
                  {
                    "type": "TEXT",
                    "id": "",
                    "nodes": [],
                    "textData": {
                      "text": "Durée maximale d'une garde à vue",
                      "decorations": [
                        {
                          "type": "LINK",
                          "linkData": {
                            "link": {
                              "url": "https://www.jplouton-avocat.fr/post/dur%C3%A9e-de-la-garde-%C3%A0-vue-24h-48h-96h-combien-de-temps-maximum",
                              "target": "SELF",
                              "rel": {
                                "nofollow": false,
                                "sponsored": false,
                                "ugc": false
                              }
                            }
                          }
                        },
                        {
                          "type": "UNDERLINE",
                          "underlineData": true
                        }
                      ]
                    }
                  }
                ],
                "paragraphData": {}
              }
            ]
          }
        ],
        "bulletedListData": {
          "indentation": 0.0
        }
      },
      {
        "type": "PARAGRAPH",
        "id": "3fs0b0spw",
        "nodes": [
          {
            "type": "TEXT",
            "id": "",
            "nodes": [],
            "textData": {
              "text": " ",
              "decorations": []
            }
          }
        ],
        "paragraphData": {}
      },
      {
        "type": "BLOCKQUOTE",
        "id": "7q3pl577",
        "nodes": [
          {
            "type": "PARAGRAPH",
            "id": "hgj9x578",
            "nodes": [
              {
                "type": "TEXT",
                "id": "",
                "nodes": [],
                "textData": {
                  "text": "Présomption d’innocence :",
                  "decorations": [
                    {
                      "type": "BOLD",
                      "fontWeightValue": 700.0
                    }
                  ]
                }
              },
              {
                "type": "TEXT",
                "id": "",
                "nodes": [],
                "textData": {
                  "text": " notre cliente, comme toute personne poursuivie, bénéficie jusqu’à décision définitive de la présomption d’innocence.",
                  "decorations": []
                }
              }
            ],
            "paragraphData": {
              "textStyle": {
                "textAlignment": "AUTO"
              },
              "indentation": 0.0
            }
          }
        ],
        "blockquoteData": {
          "indentation": 0.0
        }
      },
      {
        "type": "PARAGRAPH",
        "id": "icursgpgtg",
        "nodes": [
          {
            "type": "TEXT",
            "id": "",
            "nodes": [],
            "textData": {
              "text": " ",
              "decorations": []
            }
          }
        ],
        "paragraphData": {}
      },
      {
        "type": "HEADING",
        "id": "ukgabdspew",
        "nodes": [
          {
            "type": "TEXT",
            "id": "",
            "nodes": [],
            "textData": {
              "text": "Notre argumentation : un acte de poursuite doit être clair, précis et individualisé",
              "decorations": []
            }
          }
        ],
        "headingData": {
          "level": 2.0
        }
      },
      {
        "type": "PARAGRAPH",
        "id": "mpppa5ypyq",
        "nodes": [
          {
            "type": "TEXT",
            "id": "",
            "nodes": [],
            "textData": {
              "text": "Nous avons soulevé, ",
              "decorations": []
            }
          },
          {
            "type": "TEXT",
            "id": "",
            "nodes": [],
            "textData": {
              "text": "avant toute défense au fond",
              "decorations": [
                {
                  "type": "BOLD"
                }
              ]
            }
          },
          {
            "type": "TEXT",
            "id": "",
            "nodes": [],
            "textData": {
              "text": ", la ",
              "decorations": []
            }
          },
          {
            "type": "TEXT",
            "id": "",
            "nodes": [],
            "textData": {
              "text": "nullité de la COPJ du 20 mai 2025",
              "decorations": [
                {
                  "type": "BOLD"
                }
              ]
            }
          },
          {
            "type": "TEXT",
            "id": "",
            "nodes": [],
            "textData": {
              "text": ", sur le fondement de l'",
              "decorations": []
            }
          },
          {
            "type": "TEXT",
            "id": "",
            "nodes": [],
            "textData": {
              "text": "article 551 du Code de procédure pénale",
              "decorations": [
                {
                  "type": "BOLD"
                }
              ]
            }
          },
          {
            "type": "TEXT",
            "id": "",
            "nodes": [],
            "textData": {
              "text": ". Ce texte impose qu'une personne poursuivie soit ",
              "decorations": []
            }
          },
          {
            "type": "TEXT",
            "id": "",
            "nodes": [],
            "textData": {
              "text": "informée de manière détaillée de la nature et de la cause de la prévention",
              "decorations": [
                {
                  "type": "BOLD"
                }
              ]
            }
          },
          {
            "type": "TEXT",
            "id": "",
            "nodes": [],
            "textData": {
              "text": ", afin de ",
              "decorations": []
            }
          },
          {
            "type": "TEXT",
            "id": "",
            "nodes": [],
            "textData": {
              "text": "préparer utilement sa défense",
              "decorations": [
                {
                  "type": "BOLD"
                }
              ]
            }
          },
          {
            "type": "TEXT",
            "id": "",
            "nodes": [],
            "textData": {
              "text": ".",
              "decorations": []
            }
          }
        ],
        "paragraphData": {}
      },
      {
        "type": "PARAGRAPH",
        "id": "x779ho16vg",
        "nodes": [
          {
            "type": "TEXT",
            "id": "",
            "nodes": [],
            "textData": {
              "text": " ",
              "decorations": []
            }
          }
        ],
        "paragraphData": {}
      },
      {
        "type": "HEADING",
        "id": "qpst39etzq",
        "nodes": [
          {
            "type": "TEXT",
            "id": "",
            "nodes": [],
            "textData": {
              "text": "Les irrégularités majeures relevées dans la COPJ",
              "decorations": []
            }
          }
        ],
        "headingData": {
          "level": 3.0
        }
      },
      {
        "type": "BULLETED_LIST",
        "id": "gguieixaca",
        "nodes": [
          {
            "type": "LIST_ITEM",
            "id": "xhwaswxlrq",
            "nodes": [
              {
                "type": "PARAGRAPH",
                "id": "mbbleoynuw",
                "nodes": [
                  {
                    "type": "TEXT",
                    "id": "",
                    "nodes": [],
                    "textData": {
                      "text": "Lieux des faits",
                      "decorations": [
                        {
                          "type": "BOLD"
                        }
                      ]
                    }
                  },
                  {
                    "type": "TEXT",
                    "id": "",
                    "nodes": [],
                    "textData": {
                      "text": " : cinq chefs mentionnaient seulement ",
                      "decorations": []
                    }
                  },
                  {
                    "type": "TEXT",
                    "id": "",
                    "nodes": [],
                    "textData": {
                      "text": "« INDETERMINE EN FRANCE »",
                      "decorations": [
                        {
                          "type": "ITALIC"
                        }
                      ]
                    }
                  },
                  {
                    "type": "TEXT",
                    "id": "",
                    "nodes": [],
                    "textData": {
                      "text": ", sans localisation exploitable.",
                      "decorations": []
                    }
                  }
                ],
                "paragraphData": {}
              }
            ]
          },
          {
            "type": "LIST_ITEM",
            "id": "suuyalwl2g",
            "nodes": [
              {
                "type": "PARAGRAPH",
                "id": "nayawxvya",
                "nodes": [
                  {
                    "type": "TEXT",
                    "id": "",
                    "nodes": [],
                    "textData": {
                      "text": "Description des faits",
                      "decorations": [
                        {
                          "type": "BOLD"
                        }
                      ]
                    }
                  },
                  {
                    "type": "TEXT",
                    "id": "",
                    "nodes": [],
                    "textData": {
                      "text": " : libellés ",
                      "decorations": []
                    }
                  },
                  {
                    "type": "TEXT",
                    "id": "",
                    "nodes": [],
                    "textData": {
                      "text": "génériques",
                      "decorations": [
                        {
                          "type": "BOLD"
                        }
                      ]
                    }
                  },
                  {
                    "type": "TEXT",
                    "id": "",
                    "nodes": [],
                    "textData": {
                      "text": " (formules d'incrimination type ",
                      "decorations": []
                    }
                  },
                  {
                    "type": "TEXT",
                    "id": "",
                    "nodes": [],
                    "textData": {
                      "text": "manœuvres frauduleuses",
                      "decorations": [
                        {
                          "type": "ITALIC"
                        }
                      ]
                    }
                  },
                  {
                    "type": "TEXT",
                    "id": "",
                    "nodes": [],
                    "textData": {
                      "text": ", ",
                      "decorations": []
                    }
                  },
                  {
                    "type": "TEXT",
                    "id": "",
                    "nodes": [],
                    "textData": {
                      "text": "fausses réussites",
                      "decorations": [
                        {
                          "type": "ITALIC"
                        }
                      ]
                    }
                  },
                  {
                    "type": "TEXT",
                    "id": "",
                    "nodes": [],
                    "textData": {
                      "text": ", ",
                      "decorations": []
                    }
                  },
                  {
                    "type": "TEXT",
                    "id": "",
                    "nodes": [],
                    "textData": {
                      "text": "délivrance indue",
                      "decorations": [
                        {
                          "type": "ITALIC"
                        }
                      ]
                    }
                  },
                  {
                    "type": "TEXT",
                    "id": "",
                    "nodes": [],
                    "textData": {
                      "text": "), ",
                      "decorations": []
                    }
                  },
                  {
                    "type": "TEXT",
                    "id": "",
                    "nodes": [],
                    "textData": {
                      "text": "sans faits précis, dates ni personnes identifiées",
                      "decorations": [
                        {
                          "type": "BOLD"
                        }
                      ]
                    }
                  },
                  {
                    "type": "TEXT",
                    "id": "",
                    "nodes": [],
                    "textData": {
                      "text": ".",
                      "decorations": []
                    }
                  }
                ],
                "paragraphData": {}
              }
            ]
          },
          {
            "type": "LIST_ITEM",
            "id": "fm10negnja",
            "nodes": [
              {
                "type": "PARAGRAPH",
                "id": "usxskgirq",
                "nodes": [
                  {
                    "type": "TEXT",
                    "id": "",
                    "nodes": [],
                    "textData": {
                      "text": "Erreur de qualité",
                      "decorations": [
                        {
                          "type": "BOLD"
                        }
                      ]
                    }
                  },
                  {
                    "type": "TEXT",
                    "id": "",
                    "nodes": [],
                    "textData": {
                      "text": " : la citation prêtait à Mme T. une ",
                      "decorations": []
                    }
                  },
                  {
                    "type": "TEXT",
                    "id": "",
                    "nodes": [],
                    "textData": {
                      "text": "qualité d'« examinateur »",
                      "decorations": [
                        {
                          "type": "BOLD"
                        }
                      ]
                    }
                  },
                  {
                    "type": "TEXT",
                    "id": "",
                    "nodes": [],
                    "textData": {
                      "text": " qu'elle ",
                      "decorations": []
                    }
                  },
                  {
                    "type": "TEXT",
                    "id": "",
                    "nodes": [],
                    "textData": {
                      "text": "n'a jamais exercée",
                      "decorations": [
                        {
                          "type": "BOLD"
                        }
                      ]
                    }
                  },
                  {
                    "type": "TEXT",
                    "id": "",
                    "nodes": [],
                    "textData": {
                      "text": ".",
                      "decorations": []
                    }
                  }
                ],
                "paragraphData": {}
              }
            ]
          },
          {
            "type": "LIST_ITEM",
            "id": "rfnytowya",
            "nodes": [
              {
                "type": "PARAGRAPH",
                "id": "u4er0diuxw",
                "nodes": [
                  {
                    "type": "TEXT",
                    "id": "",
                    "nodes": [],
                    "textData": {
                      "text": "Ambiguïté sur la qualité de comparution",
                      "decorations": [
                        {
                          "type": "BOLD"
                        }
                      ]
                    }
                  },
                  {
                    "type": "TEXT",
                    "id": "",
                    "nodes": [],
                    "textData": {
                      "text": " : incertitude sur une poursuite ",
                      "decorations": []
                    }
                  },
                  {
                    "type": "TEXT",
                    "id": "",
                    "nodes": [],
                    "textData": {
                      "text": "à titre personnel",
                      "decorations": [
                        {
                          "type": "BOLD"
                        }
                      ]
                    }
                  },
                  {
                    "type": "TEXT",
                    "id": "",
                    "nodes": [],
                    "textData": {
                      "text": " ou ",
                      "decorations": []
                    }
                  },
                  {
                    "type": "TEXT",
                    "id": "",
                    "nodes": [],
                    "textData": {
                      "text": "en qualité de dirigeante",
                      "decorations": [
                        {
                          "type": "BOLD"
                        }
                      ]
                    }
                  },
                  {
                    "type": "TEXT",
                    "id": "",
                    "nodes": [],
                    "textData": {
                      "text": ", entravant l'organisation de la défense.",
                      "decorations": []
                    }
                  }
                ],
                "paragraphData": {}
              }
            ]
          }
        ],
        "bulletedListData": {
          "indentation": 0.0
        }
      },
      {
        "type": "PARAGRAPH",
        "id": "vlpsvfhg",
        "nodes": [
          {
            "type": "TEXT",
            "id": "",
            "nodes": [],
            "textData": {
              "text": " ",
              "decorations": []
            }
          }
        ],
        "paragraphData": {}
      },
      {
        "type": "PARAGRAPH",
        "id": "2n1ew4kisa",
        "nodes": [
          {
            "type": "TEXT",
            "id": "",
            "nodes": [],
            "textData": {
              "text": "L'acte de poursuite doit également permettre d'identifier les périodes ",
              "decorations": []
            }
          },
          {
            "type": "TEXT",
            "id": "",
            "nodes": [],
            "textData": {
              "text": "au regard de la prescription pénale",
              "decorations": [
                {
                  "type": "BOLD"
                }
              ]
            }
          },
          {
            "type": "TEXT",
            "id": "",
            "nodes": [],
            "textData": {
              "text": ". Pour un rappel clair des délais et des règles applicables : ",
              "decorations": []
            }
          },
          {
            "type": "TEXT",
            "id": "",
            "nodes": [],
            "textData": {
              "text": "Réforme de la prescription pénale : comprendre les délais",
              "decorations": [
                {
                  "type": "LINK",
                  "linkData": {
                    "link": {
                      "url": "https://www.jplouton-avocat.fr/post/réforme-de-la-prescription-pénale-comprendre-les-délais-et-les-nouvelles-règles",
                      "target": "SELF",
                      "rel": {
                        "nofollow": false,
                        "sponsored": false,
                        "ugc": false
                      }
                    }
                  }
                },
                {
                  "type": "UNDERLINE",
                  "underlineData": true
                }
              ]
            }
          },
          {
            "type": "TEXT",
            "id": "",
            "nodes": [],
            "textData": {
              "text": ".",
              "decorations": []
            }
          }
        ],
        "paragraphData": {}
      },
      {
        "type": "PARAGRAPH",
        "id": "breu9phxaq",
        "nodes": [
          {
            "type": "TEXT",
            "id": "",
            "nodes": [],
            "textData": {
              "text": " ",
              "decorations": []
            }
          }
        ],
        "paragraphData": {}
      },
      {
        "type": "HEADING",
        "id": "yzcd8wxokg",
        "nodes": [
          {
            "type": "TEXT",
            "id": "",
            "nodes": [],
            "textData": {
              "text": "La décision du Tribunal correctionnel de Bordeaux du 8 septembre 2025",
              "decorations": []
            }
          }
        ],
        "headingData": {
          "level": 2.0
        }
      },
      {
        "type": "PARAGRAPH",
        "id": "2pdrbpvyqg",
        "nodes": [
          {
            "type": "TEXT",
            "id": "",
            "nodes": [],
            "textData": {
              "text": "Le Tribunal correctionnel de Bordeaux a ",
              "decorations": []
            }
          },
          {
            "type": "TEXT",
            "id": "",
            "nodes": [],
            "textData": {
              "text": "acquiescé à notre exception de nullité",
              "decorations": [
                {
                  "type": "BOLD"
                }
              ]
            }
          },
          {
            "type": "TEXT",
            "id": "",
            "nodes": [],
            "textData": {
              "text": " : la ",
              "decorations": []
            }
          },
          {
            "type": "TEXT",
            "id": "",
            "nodes": [],
            "textData": {
              "text": "COPJ est annulée",
              "decorations": [
                {
                  "type": "BOLD"
                }
              ]
            }
          },
          {
            "type": "TEXT",
            "id": "",
            "nodes": [],
            "textData": {
              "text": " et le ",
              "decorations": []
            }
          },
          {
            "type": "TEXT",
            "id": "",
            "nodes": [],
            "textData": {
              "text": "ministère public est renvoyé à mieux se pourvoir",
              "decorations": [
                {
                  "type": "BOLD"
                }
              ]
            }
          },
          {
            "type": "TEXT",
            "id": "",
            "nodes": [],
            "textData": {
              "text": ".",
              "decorations": []
            }
          }
        ],
        "paragraphData": {}
      },
      {
        "type": "PARAGRAPH",
        "id": "05e6aguaiq",
        "nodes": [
          {
            "type": "TEXT",
            "id": "",
            "nodes": [],
            "textData": {
              "text": " ",
              "decorations": []
            }
          }
        ],
        "paragraphData": {}
      },
      {
        "type": "PARAGRAPH",
        "id": "kd85sg6m5a",
        "nodes": [
          {
            "type": "TEXT",
            "id": "",
            "nodes": [],
            "textData": {
              "text": "En pratique, ",
              "decorations": []
            }
          },
          {
            "type": "TEXT",
            "id": "",
            "nodes": [],
            "textData": {
              "text": "la procédure engagée sur la base de cet acte irrégulier est écartée",
              "decorations": [
                {
                  "type": "BOLD"
                }
              ]
            }
          },
          {
            "type": "TEXT",
            "id": "",
            "nodes": [],
            "textData": {
              "text": ". Le parquet reste libre, s'il l'estime opportun et dans les délais légaux, de ",
              "decorations": []
            }
          },
          {
            "type": "TEXT",
            "id": "",
            "nodes": [],
            "textData": {
              "text": "reprendre des poursuites régulières",
              "decorations": [
                {
                  "type": "BOLD"
                }
              ]
            }
          },
          {
            "type": "TEXT",
            "id": "",
            "nodes": [],
            "textData": {
              "text": " par un acte conforme.",
              "decorations": []
            }
          }
        ],
        "paragraphData": {}
      },
      {
        "type": "PARAGRAPH",
        "id": "uxvk3ofbpw",
        "nodes": [
          {
            "type": "TEXT",
            "id": "",
            "nodes": [],
            "textData": {
              "text": " ",
              "decorations": []
            }
          }
        ],
        "paragraphData": {}
      },
      {
        "type": "HEADING",
        "id": "gvze55uh5q",
        "nodes": [
          {
            "type": "TEXT",
            "id": "",
            "nodes": [],
            "textData": {
              "text": "Ce qu'il faut retenir sur la nullité de la poursuite",
              "decorations": []
            }
          }
        ],
        "headingData": {
          "level": 2.0
        }
      },
      {
        "type": "BULLETED_LIST",
        "id": "ddgd6rk92a",
        "nodes": [
          {
            "type": "LIST_ITEM",
            "id": "ax9xlh12qw",
            "nodes": [
              {
                "type": "PARAGRAPH",
                "id": "lhqxxemeiw",
                "nodes": [
                  {
                    "type": "TEXT",
                    "id": "",
                    "nodes": [],
                    "textData": {
                      "text": "Une ",
                      "decorations": []
                    }
                  },
                  {
                    "type": "TEXT",
                    "id": "",
                    "nodes": [],
                    "textData": {
                      "text": "citation imprécise",
                      "decorations": [
                        {
                          "type": "BOLD"
                        }
                      ]
                    }
                  },
                  {
                    "type": "TEXT",
                    "id": "",
                    "nodes": [],
                    "textData": {
                      "text": " (faits génériques, lieux indéterminés, absence de qualité ou d'individualisation) ",
                      "decorations": []
                    }
                  },
                  {
                    "type": "TEXT",
                    "id": "",
                    "nodes": [],
                    "textData": {
                      "text": "porte atteinte aux droits de la défense",
                      "decorations": [
                        {
                          "type": "BOLD"
                        }
                      ]
                    }
                  },
                  {
                    "type": "TEXT",
                    "id": "",
                    "nodes": [],
                    "textData": {
                      "text": " et ",
                      "decorations": []
                    }
                  },
                  {
                    "type": "TEXT",
                    "id": "",
                    "nodes": [],
                    "textData": {
                      "text": "peut être annulée",
                      "decorations": [
                        {
                          "type": "BOLD"
                        }
                      ]
                    }
                  },
                  {
                    "type": "TEXT",
                    "id": "",
                    "nodes": [],
                    "textData": {
                      "text": ".",
                      "decorations": []
                    }
                  }
                ],
                "paragraphData": {}
              }
            ]
          },
          {
            "type": "LIST_ITEM",
            "id": "ndaok6q",
            "nodes": [
              {
                "type": "PARAGRAPH",
                "id": "ghxsbrcl9g",
                "nodes": [
                  {
                    "type": "TEXT",
                    "id": "",
                    "nodes": [],
                    "textData": {
                      "text": "La ",
                      "decorations": []
                    }
                  },
                  {
                    "type": "TEXT",
                    "id": "",
                    "nodes": [],
                    "textData": {
                      "text": "nullité de la poursuite",
                      "decorations": [
                        {
                          "type": "BOLD"
                        }
                      ]
                    }
                  },
                  {
                    "type": "TEXT",
                    "id": "",
                    "nodes": [],
                    "textData": {
                      "text": " n'est ",
                      "decorations": []
                    }
                  },
                  {
                    "type": "TEXT",
                    "id": "",
                    "nodes": [],
                    "textData": {
                      "text": "pas",
                      "decorations": [
                        {
                          "type": "BOLD"
                        }
                      ]
                    }
                  },
                  {
                    "type": "TEXT",
                    "id": "",
                    "nodes": [],
                    "textData": {
                      "text": " une décision au fond : c'est le ",
                      "decorations": []
                    }
                  },
                  {
                    "type": "TEXT",
                    "id": "",
                    "nodes": [],
                    "textData": {
                      "text": "contrôle de la régularité",
                      "decorations": [
                        {
                          "type": "BOLD"
                        }
                      ]
                    }
                  },
                  {
                    "type": "TEXT",
                    "id": "",
                    "nodes": [],
                    "textData": {
                      "text": " de l'acte de saisine.",
                      "decorations": []
                    }
                  }
                ],
                "paragraphData": {}
              }
            ]
          },
          {
            "type": "LIST_ITEM",
            "id": "rqw1esa6kw",
            "nodes": [
              {
                "type": "PARAGRAPH",
                "id": "tbab3o5mq",
                "nodes": [
                  {
                    "type": "TEXT",
                    "id": "",
                    "nodes": [],
                    "textData": {
                      "text": "Vous avez reçu une convocation, vous êtes auditionné ou placé en garde à vue ? Consultez nos ressources et ",
                      "decorations": []
                    }
                  },
                  {
                    "type": "TEXT",
                    "id": "",
                    "nodes": [],
                    "textData": {
                      "text": "faites vérifier votre situation par un avocat pénaliste",
                      "decorations": [
                        {
                          "type": "BOLD"
                        }
                      ]
                    }
                  },
                  {
                    "type": "TEXT",
                    "id": "",
                    "nodes": [],
                    "textData": {
                      "text": ".",
                      "decorations": []
                    }
                  }
                ],
                "paragraphData": {}
              }
            ]
          }
        ],
        "bulletedListData": {
          "indentation": 0.0
        }
      },
      {
        "type": "PARAGRAPH",
        "id": "k8hfgrbfka",
        "nodes": [
          {
            "type": "TEXT",
            "id": "",
            "nodes": [],
            "textData": {
              "text": " ",
              "decorations": []
            }
          }
        ],
        "paragraphData": {}
      },
      {
        "type": "DIVIDER",
        "id": "vydzeru1nq",
        "nodes": [],
        "dividerData": {
          "lineStyle": "SINGLE",
          "width": "LARGE",
          "alignment": "CENTER"
        }
      },
      {
        "type": "PARAGRAPH",
        "id": "poaquljwsw",
        "nodes": [
          {
            "type": "TEXT",
            "id": "",
            "nodes": [],
            "textData": {
              "text": " ",
              "decorations": []
            }
          }
        ],
        "paragraphData": {}
      },
      {
        "type": "HEADING",
        "id": "nfruorcpxa",
        "nodes": [
          {
            "type": "TEXT",
            "id": "",
            "nodes": [],
            "textData": {
              "text": "Pour aller plus loin",
              "decorations": []
            }
          }
        ],
        "headingData": {
          "level": 2.0
        }
      },
      {
        "type": "BULLETED_LIST",
        "id": "e3clzrhcdg",
        "nodes": [
          {
            "type": "LIST_ITEM",
            "id": "zuhbsbwyq",
            "nodes": [
              {
                "type": "PARAGRAPH",
                "id": "kfm8o9nx7a",
                "nodes": [
                  {
                    "type": "TEXT",
                    "id": "",
                    "nodes": [],
                    "textData": {
                      "text": "Porter plainte efficacement",
                      "decorations": [
                        {
                          "type": "LINK",
                          "linkData": {
                            "link": {
                              "url": "https://www.jplouton-avocat.fr/post/d%C3%A9p%C3%B4t-de-plainte-en-france-comment-porter-plainte-efficacement",
                              "target": "SELF",
                              "rel": {
                                "nofollow": false,
                                "sponsored": false,
                                "ugc": false
                              }
                            }
                          }
                        },
                        {
                          "type": "UNDERLINE",
                          "underlineData": true
                        }
                      ]
                    }
                  }
                ],
                "paragraphData": {}
              }
            ]
          },
          {
            "type": "LIST_ITEM",
            "id": "h4fvvbhrga",
            "nodes": [
              {
                "type": "PARAGRAPH",
                "id": "iwwlsmikga",
                "nodes": [
                  {
                    "type": "TEXT",
                    "id": "",
                    "nodes": [],
                    "textData": {
                      "text": "Qu'est-ce que la comparution immédiate ?",
                      "decorations": [
                        {
                          "type": "LINK",
                          "linkData": {
                            "link": {
                              "url": "https://www.jplouton-avocat.fr/post/qu-est-ce-que-la-comparution-imm%C3%A9diate",
                              "target": "SELF",
                              "rel": {
                                "nofollow": false,
                                "sponsored": false,
                                "ugc": false
                              }
                            }
                          }
                        },
                        {
                          "type": "UNDERLINE",
                          "underlineData": true
                        }
                      ]
                    }
                  }
                ],
                "paragraphData": {}
              }
            ]
          },
          {
            "type": "LIST_ITEM",
            "id": "p13d7s9y6w",
            "nodes": [
              {
                "type": "PARAGRAPH",
                "id": "1s1cswxutg",
                "nodes": [
                  {
                    "type": "TEXT",
                    "id": "",
                    "nodes": [],
                    "textData": {
                      "text": "Notre expertise en droit pénal",
                      "decorations": [
                        {
                          "type": "LINK",
                          "linkData": {
                            "link": {
                              "url": "https://www.jplouton-avocat.fr/defense-penale/droit-penal",
                              "target": "SELF",
                              "rel": {
                                "nofollow": false,
                                "sponsored": false,
                                "ugc": false
                              }
                            }
                          }
                        },
                        {
                          "type": "UNDERLINE",
                          "underlineData": true
                        }
                      ]
                    }
                  }
                ],
                "paragraphData": {}
              }
            ]
          }
        ],
        "bulletedListData": {
          "indentation": 0.0
        }
      },
      {
        "type": "PARAGRAPH",
        "id": "y9h2gqlqa",
        "nodes": [
          {
            "type": "TEXT",
            "id": "",
            "nodes": [],
            "textData": {
              "text": " ",
              "decorations": []
            }
          }
        ],
        "paragraphData": {}
      },
      {
        "type": "HEADING",
        "id": "ufah3u2cq",
        "nodes": [
          {
            "type": "TEXT",
            "id": "",
            "nodes": [],
            "textData": {
              "text": "Notre engagement",
              "decorations": []
            }
          }
        ],
        "headingData": {
          "level": 2.0
        }
      },
      {
        "type": "PARAGRAPH",
        "id": "e4t4ongigq",
        "nodes": [
          {
            "type": "TEXT",
            "id": "",
            "nodes": [],
            "textData": {
              "text": "Le Cabinet ",
              "decorations": []
            }
          },
          {
            "type": "TEXT",
            "id": "",
            "nodes": [],
            "textData": {
              "text": "Julien Plouton",
              "decorations": [
                {
                  "type": "BOLD"
                }
              ]
            }
          },
          {
            "type": "TEXT",
            "id": "",
            "nodes": [],
            "textData": {
              "text": " défend, avec rigueur et humanité, les droits des personnes poursuivies comme des victimes : ",
              "decorations": []
            }
          },
          {
            "type": "TEXT",
            "id": "",
            "nodes": [],
            "textData": {
              "text": "contrôle des actes de procédure",
              "decorations": [
                {
                  "type": "BOLD"
                }
              ]
            }
          },
          {
            "type": "TEXT",
            "id": "",
            "nodes": [],
            "textData": {
              "text": ", ",
              "decorations": []
            }
          },
          {
            "type": "TEXT",
            "id": "",
            "nodes": [],
            "textData": {
              "text": "mise en état technique du dossier",
              "decorations": [
                {
                  "type": "BOLD"
                }
              ]
            }
          },
          {
            "type": "TEXT",
            "id": "",
            "nodes": [],
            "textData": {
              "text": ", ",
              "decorations": []
            }
          },
          {
            "type": "TEXT",
            "id": "",
            "nodes": [],
            "textData": {
              "text": "plaidoirie au fond",
              "decorations": [
                {
                  "type": "BOLD"
                }
              ]
            }
          },
          {
            "type": "TEXT",
            "id": "",
            "nodes": [],
            "textData": {
              "text": ".",
              "decorations": []
            }
          }
        ],
        "paragraphData": {}
      },
      {
        "type": "PARAGRAPH",
        "id": "m22smfgyjq",
        "nodes": [
          {
            "type": "TEXT",
            "id": "",
            "nodes": [],
            "textData": {
              "text": " ",
              "decorations": []
            }
          }
        ],
        "paragraphData": {}
      },
      {
        "type": "PARAGRAPH",
        "id": "bea5pqrmwg",
        "nodes": [
          {
            "type": "TEXT",
            "id": "",
            "nodes": [],
            "textData": {
              "text": "Vous êtes concerné par une convocation ou une enquête ? ",
              "decorations": []
            }
          },
          {
            "type": "TEXT",
            "id": "",
            "nodes": [],
            "textData": {
              "text": "Contactez-nous",
              "decorations": [
                {
                  "type": "BOLD"
                }
              ]
            }
          },
          {
            "type": "TEXT",
            "id": "",
            "nodes": [],
            "textData": {
              "text": " pour une analyse rapide et confidentielle.",
              "decorations": []
            }
          }
        ],
        "paragraphData": {}
      },
      {
        "type": "PARAGRAPH",
        "id": "xbszlub2hq",
        "nodes": [
          {
            "type": "TEXT",
            "id": "",
            "nodes": [],
            "textData": {
              "text": " ",
              "decorations": []
            }
          }
        ],
        "paragraphData": {}
      },
      {
        "type": "PARAGRAPH",
        "id": "5dgjlbxeba",
        "nodes": [
          {
            "type": "TEXT",
            "id": "",
            "nodes": [],
            "textData": {
              "text": "Prendre rendez-vous",
              "decorations": [
                {
                  "type": "LINK",
                  "linkData": {
                    "link": {
                      "url": "https://www.jplouton-avocat.fr/honoraires-rendez-vous",
                      "target": "SELF",
                      "rel": {
                        "nofollow": false,
                        "sponsored": false,
                        "ugc": false
                      }
                    }
                  }
                },
                {
                  "type": "UNDERLINE",
                  "underlineData": true
                }
              ]
            }
          },
          {
            "type": "TEXT",
            "id": "",
            "nodes": [],
            "textData": {
              "text": " — ",
              "decorations": []
            }
          },
          {
            "type": "TEXT",
            "id": "",
            "nodes": [],
            "textData": {
              "text": "Découvrir l'équipe",
              "decorations": [
                {
                  "type": "LINK",
                  "linkData": {
                    "link": {
                      "url": "https://www.jplouton-avocat.fr/notre-cabinet",
                      "target": "SELF",
                      "rel": {
                        "nofollow": false,
                        "sponsored": false,
                        "ugc": false
                      }
                    }
                  }
                },
                {
                  "type": "UNDERLINE",
                  "underlineData": true
                }
              ]
            }
          },
          {
            "type": "TEXT",
            "id": "",
            "nodes": [],
            "textData": {
              "text": " — ",
              "decorations": []
            }
          },
          {
            "type": "TEXT",
            "id": "",
            "nodes": [],
            "textData": {
              "text": "Accueil du cabinet",
              "decorations": [
                {
                  "type": "LINK",
                  "linkData": {
                    "link": {
                      "url": "https://www.jplouton-avocat.fr/",
                      "target": "SELF",
                      "rel": {
                        "nofollow": false,
                        "sponsored": false,
                        "ugc": false
                      }
                    }
                  }
                },
                {
                  "type": "UNDERLINE",
                  "underlineData": true
                }
              ]
            }
          }
        ],
        "paragraphData": {}
      },
      {
        "type": "PARAGRAPH",
        "id": "1jhxhd4lxq",
        "nodes": [
          {
            "type": "TEXT",
            "id": "",
            "nodes": [],
            "textData": {
              "text": " ",
              "decorations": []
            }
          }
        ],
        "paragraphData": {}
      }
    ],
    "metadata": {
      "version": 1.0,
      "createdTimestamp": "2026-05-11T17:53:32.492Z",
      "updatedTimestamp": "2026-05-11T17:53:32.492Z"
    }
  }
}
