{
  "slug": "faute-médicale-défaut-de-diagnostic-du-médecin-obstétricien-le-cabinet-obtient-une-indemnisation",
  "title": "Défaut de diagnostic échographique : 50 000 € pour les parents",
  "excerpt": "Défaut de diagnostic échographique d'une exstrophie vésicale : le TGI d'Angoulême condamne l'obstétricien à 50 000 € de dommages-intérêts (21 juin 2018).",
  "publishedAt": "2018-07-30",
  "updatedAt": "2025-04-03",
  "status": "published",
  "author": "07454f1f-c54a-4308-b897-19be554db88a",
  "categories": [
    "Accidents et erreurs médicales",
    "Victimes de délits ou crimes"
  ],
  "categoryIds": [
    "6798cd544011366b8aea5e9d",
    "6798cf3b003803362e6d9def"
  ],
  "coverImage": "/media/blog-covers/faute-medicale-defaut-de-diagnostic-du-medecin-obstetricien-le-cabinet-obtient-u.jpg",
  "minutesToRead": 4,
  "viewCount": 231,
  "url": "/post/faute-médicale-défaut-de-diagnostic-du-médecin-obstétricien-le-cabinet-obtient-une-indemnisation",
  "wixId": "6798f18a9981b29b293b7299",
  "bodyHtml": "<p><strong>En résumé : Le Tribunal de Grande Instance d&#x27;Angoulême a condamné le 21 juin 2018 un gynécologue obstétricien à verser 50 000 € à des parents pour défaut de diagnostic échographique d&#x27;une exstrophie vésicale. La juridiction a reconnu une faute médicale au sens de l&#x27;article L114-5 du Code de l&#x27;action sociale et des familles, malgré un rapport d&#x27;expertise concluant à l&#x27;absence de faute.</strong></p>\n<p><em>Tribunal de Grande Instance d&#x27;ANGOULEME, 1ère Chambre civile, 21 juin 2018, RG n°14/00384</em></p>\n<h2>Les faits : un suivi obstétrical sans alerte malgré une malformation grave</h2>\n<p>Au cours de sa grossesse, Madame D. était suivie par le Docteur D., gynécologue obstétricien. Ce dernier assurait l&#x27;intégralité du suivi de la future maman et effectuait 3 échographies à 12, 22 et 31 semaines d&#x27;aménorrhées.</p>\n<p>A l&#x27;issue de chaque échographie, le Docteur D. concluait à l&#x27;absence de malformation fœtale. Lors de la troisième échographie, il indiquait aux futurs parents que l&#x27;enfant serait de sexe masculin.</p>\n<p>Les comptes rendus de chaque échographie portaient notamment mention de l&#x27;absence d&#x27;anomalie et précisaient que la vessie était de position et de volume normaux.</p>\n<p>Toutefois, à la naissance de l&#x27;enfant, outre le fait qu&#x27;il ne s&#x27;agissait en réalité pas d&#x27;un garçon mais d&#x27;une fille, il apparaissait que l&#x27;enfant était atteint de graves lésions consécutives à une exstrophie vésicale. Cette malformation complexe des voies urogénitales affecte notamment le fonctionnement de la vessie, peut grever à long terme le diagnostic vital et limite considérablement le taux de fertilité.</p>\n<h2>L&#x27;action en responsabilité médicale devant le TGI d&#x27;Angoulême</h2>\n<p>Les parents assignaient l&#x27;obstétricien et son assureur devant le Tribunal de Grande Instance d&#x27;Angoulême. L&#x27;objectif : faire reconnaître la responsabilité du médecin et obtenir réparation de leurs préjudices.</p>\n<p>En cours de procédure, les demandeurs sollicitaient une expertise médicale. Cette mesure visait à déterminer si le suivi obstétrical était conforme à la bonne pratique et aux données acquises de la science médicale, et si le Docteur D. avait commis une faute dans ledit suivi.</p>\n<h2>Une expertise médicale contestée par le cabinet</h2>\n<p>En date du 11 mai 2015, l&#x27;expert rendait son rapport. Celui-ci concluait, de façon pour le moins surprenante, à l&#x27;absence de faute et de responsabilité du médecin.</p>\n<p>L&#x27;expert considérait notamment que les examens échographiques effectués par le Docteur D. étaient attentifs, diligents et conformes aux bonnes pratiques obstétricales. Selon lui, aucune faute ne pouvait être retenue à son encontre.</p>\n<p>Il précisait par ailleurs que le taux de diagnostic par échographie de l&#x27;exstrophie vésicale était extrêmement faible, de l&#x27;ordre de 8 %. Il soulignait toutefois que ladite pathologie pouvait être dépistée en anténatal.</p>\n<h3>Les critiques portées contre le rapport d&#x27;expertise</h3>\n<p>Dans le cadre de dires adressés à l&#x27;expert, nous soulevions un certain nombre d&#x27;observations destinées à critiquer les conclusions de son rapport.</p>\n<p>Il apparaissait parfaitement incompréhensible de conclure à l&#x27;absence de faute du médecin dans le suivi obstétrical. Ce dernier avait pourtant affirmé à 3 reprises et sans le moindre doute avoir visualisé parfaitement un organe, la vessie, dont l&#x27;enfant était pourtant dépourvu.</p>\n<p>Par ailleurs, les statistiques retenues par l&#x27;expert quant au taux de diagnostic de l&#x27;exstrophie vésicale apparaissaient largement sous-évaluées. D&#x27;autres études relevaient, entre 2003 et 2009, période au cours de laquelle les échographies étaient effectuées, un taux de diagnostic de 33 %, bien supérieur au taux de 8 % retenu par l&#x27;expert.</p>\n<h2>La reconnaissance de la faute médicale par le Tribunal</h2>\n<p>Le Tribunal de Grande Instance d&#x27;Angoulême décidait in fine, chose rare dans ce type de dossier, d&#x27;aller à l&#x27;encontre des conclusions de l&#x27;expert. La juridiction faisait droit à notre analyse du dossier et retenait la faute médicale.</p>\n<p>Le Tribunal soulignait que le Docteur D. avait, sans restriction ni doute possible, indiqué de manière erronée que la vessie était visible lors des trois échographies. Cette visualisation erronée a conduit à l&#x27;absence de diagnostic, identification erronée constitutive d&#x27;une faute caractérisée au sens de l&#x27;article L114-5 du code de la santé publique.</p>\n<p>Le Tribunal ajoutait que malgré le caractère curable d&#x27;une exstrophie vésicale, son diagnostic reste une indication potentielle d&#x27;interruption médicale de grossesse. La juridiction motivait sa décision par la gravité de cette affection, les multiples opérations nécessaires à sa cure et les pronostics incertains aux niveaux rénal, vésical, sexuel et obstétrical, avec de lourdes implications psychologiques et sociales.</p>\n<h2>L&#x27;indemnisation accordée aux parents : 50 000 euros</h2>\n<p>Le Tribunal concluait qu&#x27;il est incontestable que les parents ont été privés de la chance d&#x27;avoir recours à une interruption médicale de grossesse. Ce préjudice a été réparé à hauteur de 20 000 euros.</p>\n<p>Par ailleurs, la situation difficile vécue par les parents du fait du handicap de leur fille, la nécessité récurrente de soins de plus en plus stressants et le fait que le couple a été mis à mal par cette épreuve justifiaient une seconde indemnisation. Le Tribunal allouait ainsi la somme de 30 000 euros au titre du préjudice moral né de l&#x27;impréparation au handicap de leur enfant.</p>\n<p>La décomposition de l&#x27;indemnisation est la suivante :</p>\n<ul><li><strong>20 000 €</strong> au titre de la perte de chance de recourir à une interruption médicale de grossesse</li><li><strong>30 000 €</strong> au titre du préjudice moral lié à l&#x27;impréparation au handicap</li><li><strong>Total : 50 000 €</strong> de dommages-intérêts</li></ul>\n<p>La partie adverse a décidé de ne pas interjeter appel et de s&#x27;exécuter volontairement.</p>\n<p>Cette affaire souligne l&#x27;importance de consulter un <a href=\"/indemnisation-des-victimes/accidents-et-erreurs-medicales\">avocat spécialisé en responsabilité médicale</a> pour faire valoir les droits des victimes de fautes médicales.</p>",
  "body": [
    "En résumé : Le Tribunal de Grande Instance d'Angoulême a condamné le 21 juin 2018 un gynécologue obstétricien à verser 50 000 € à des parents pour défaut de diagnostic échographique d'une exstrophie vésicale. La juridiction a reconnu une faute médicale au sens de l'article L114-5 du Code de l'action sociale et des familles, malgré un rapport d'expertise concluant à l'absence de faute. Tribunal de Grande Instance d'ANGOULEME, 1ère Chambre civile, 21 juin 2018, RG n°14/00384 Les faits : un suivi obstétrical sans alerte malgré une malformation grave Au cours de sa grossesse, Madame D. était suivie par le Docteur D., gynécologue obstétricien. Ce dernier assurait l'intégralité du suivi de la future maman et effectuait 3 échographies à 12, 22 et 31 semaines d'aménorrhées. A l'issue de chaque échographie, le Docteur D. concluait à l'absence de malformation fœtale. Lors de la troisième échographie, il indiquait aux futurs parents que l'enfant serait de sexe masculin. Les comptes rendus de chaque échographie portaient notamment mention de l'absence d'anomalie et précisaient que la vessie était de position et de volume normaux. Toutefois, à la naissance de l'enfant, outre le fait qu'il ne s'agissait en réalité pas d'un garçon mais d'une fille, il apparaissait que l'enfant était atteint de graves lésions consécutives à une exstrophie vésicale. Cette malformation complexe des voies urogénitales affecte notamment le fonctionnement de la vessie, peut grever à long terme le diagnostic vital et limite considérablement le taux de fertilité. L'action en responsabilité médicale devant le TGI d'Angoulême Les parents assignaient l'obstétricien et son assureur devant le Tribunal de Grande Instance d'Angoulême. L'objectif : faire reconnaître la responsabilité du médecin et obtenir réparation de leurs préjudices. En cours de procédure, les demandeurs sollicitaient une expertise médicale. Cette mesure visait à déterminer si le suivi obstétrical était conforme à la bonne pratique et aux données acquises de la science médicale, et si le Docteur D. avait commis une faute dans ledit suivi. Une expertise médicale contestée par le cabinet En date du 11 mai 2015, l'expert rendait son rapport. Celui-ci concluait, de façon pour le moins surprenante, à l'absence de faute et de responsabilité du médecin. L'expert considérait notamment que les examens échographiques effectués par le Docteur D. étaient attentifs, diligents et conformes aux bonnes pratiques obstétricales. Selon lui, aucune faute ne pouvait être retenue à son encontre. Il précisait par ailleurs que le taux de diagnostic par échographie de l'exstrophie vésicale était extrêmement faible, de l'ordre de 8 %. Il soulignait toutefois que ladite pathologie pouvait être dépistée en anténatal. Les critiques portées contre le rapport d'expertise Dans le cadre de dires adressés à l'expert, nous soulevions un certain nombre d'observations destinées à critiquer les conclusions de son rapport. Il apparaissait parfaitement incompréhensible de conclure à l'absence de faute du médecin dans le suivi obstétrical. Ce dernier avait pourtant affirmé à 3 reprises et sans le moindre doute avoir visualisé parfaitement un organe, la vessie, dont l'enfant était pourtant dépourvu. Par ailleurs, les statistiques retenues par l'expert quant au taux de diagnostic de l'exstrophie vésicale apparaissaient largement sous-évaluées. D'autres études relevaient, entre 2003 et 2009, période au cours de laquelle les échographies étaient effectuées, un taux de diagnostic de 33 %, bien supérieur au taux de 8 % retenu par l'expert. La reconnaissance de la faute médicale par le Tribunal Le Tribunal de Grande Instance d'Angoulême décidait in fine, chose rare dans ce type de dossier, d'aller à l'encontre des conclusions de l'expert. La juridiction faisait droit à notre analyse du dossier et retenait la faute médicale. Le Tribunal soulignait que le Docteur D. avait, sans restriction ni doute possible, indiqué de manière erronée que la vessie était visible lors des trois échographies. Cette visualisation erronée a conduit à l'absence de diagnostic, identification erronée constitutive d'une faute caractérisée au sens de l'article L114-5 du code de la santé publique. Le Tribunal ajoutait que malgré le caractère curable d'une exstrophie vésicale, son diagnostic reste une indication potentielle d'interruption médicale de grossesse. La juridiction motivait sa décision par la gravité de cette affection, les multiples opérations nécessaires à sa cure et les pronostics incertains aux niveaux rénal, vésical, sexuel et obstétrical, avec de lourdes implications psychologiques et sociales. L'indemnisation accordée aux parents : 50 000 euros Le Tribunal concluait qu'il est incontestable que les parents ont été privés de la chance d'avoir recours à une interruption médicale de grossesse. Ce préjudice a été réparé à hauteur de 20 000 euros. Par ailleurs, la situation difficile vécue par les parents du fait du handicap de leur fille, la nécessité récurrente de soins de plus en plus stressants et le fait que le couple a été mis à mal par cette épreuve justifiaient une seconde indemnisation. Le Tribunal allouait ainsi la somme de 30 000 euros au titre du préjudice moral né de l'impréparation au handicap de leur enfant. La décomposition de l'indemnisation est la suivante : 20 000 € au titre de la perte de chance de recourir à une interruption médicale de grossesse 30 000 € au titre du préjudice moral lié à l'impréparation au handicap Total : 50 000 € de dommages-intérêts La partie adverse a décidé de ne pas interjeter appel et de s'exécuter volontairement. Cette affaire souligne l'importance de consulter un avocat spécialisé en responsabilité médicale pour faire valoir les droits des victimes de fautes médicales."
  ],
  "coverImageWix": "https://static.wixstatic.com/media/nsplsh_6b9b3772e50a498f93e8eae4daece692~mv2.jpg"
}
