{"type":"doc","content":[{"type":"paragraph","content":[{"type":"text","text":"Pourquoi engager la responsabilité de l’État ? "},{"type":"text","text":"Lorsqu’un drame survient malgré des alertes répétées, la question de la responsabilité des institutions peut se poser","marks":[{"type":"bold"}]},{"type":"text","text":". Le "},{"type":"text","text":"féminicide de ","marks":[{"type":"link","attrs":{"href":"/post/revue-de-presse-affaire-chahinez-daoud-plouton"}},{"type":"underline"}]},{"type":"text","text":"Chahinez Daoud","marks":[{"type":"bold"},{"type":"link","attrs":{"href":"/post/revue-de-presse-affaire-chahinez-daoud-plouton"}},{"type":"underline"}]},{"type":"text","text":", commis le 4 mai 2021 à "},{"type":"text","text":"Mérignac","marks":[{"type":"bold"}]},{"type":"text","text":", en est une illustration tragique. Malgré plusieurs plaintes et signalements, aucune mesure de protection efficace n’a empêché le passage à l’acte."}]},{"type":"paragraph","content":[{"type":"text","text":""}]},{"type":"paragraph","content":[{"type":"text","text":"Dans ce contexte, une "},{"type":"text","text":"action en responsabilité pour ","marks":[{"type":"link","attrs":{"href":"/post/féminicide-de-mérignac-le-cabinet-lance-une-action-pour-faute-lourde-contre-l-etat"}},{"type":"underline"}]},{"type":"text","text":"faute lourde","marks":[{"type":"bold"},{"type":"link","attrs":{"href":"/post/féminicide-de-mérignac-le-cabinet-lance-une-action-pour-faute-lourde-contre-l-etat"}},{"type":"underline"}]},{"type":"text","text":" peut être engagée contre l’État lorsqu’un"},{"type":"text","text":" dysfonctionnement grave du service public ","marks":[{"type":"bold"}]},{"type":"text","text":"(police, justice…) a contribué au dommage."}]},{"type":"paragraph","content":[{"type":"text","text":""}]},{"type":"orderedList","content":[{"type":"listItem","content":[{"type":"heading","attrs":{"level":2},"content":[{"type":"text","text":"Qu’est-ce qu’une faute lourde ?"}]}]}]},{"type":"paragraph","content":[{"type":"text","text":"La faute lourde est une faute d’une "},{"type":"text","text":"gravité exceptionnelle","marks":[{"type":"bold"}]},{"type":"text","text":", révélant une défaillance caractérisée du service public dans l’exercice de sa mission."}]},{"type":"paragraph","content":[{"type":"text","text":""}]},{"type":"paragraph","content":[{"type":"text","text":"Elle ne correspond pas à une simple erreur d’appréciation.","marks":[{"type":"bold"}]}]},{"type":"paragraph","content":[{"type":"text","text":""}]},{"type":"paragraph","content":[{"type":"text","text":"Elle suppose :"}]},{"type":"bulletList","content":[{"type":"listItem","content":[{"type":"paragraph","content":[{"type":"text","text":"Une accumulation de manquements"}]}]},{"type":"listItem","content":[{"type":"paragraph","content":[{"type":"text","text":"Une inaction prolongée malgré des alertes claires"}]}]},{"type":"listItem","content":[{"type":"paragraph","content":[{"type":"text","text":"Une désorganisation ou une carence manifeste du service"}]},{"type":"paragraph","content":[{"type":"text","text":""}]}]}]},{"type":"paragraph","content":[{"type":"text","text":"En matière judiciaire, le fondement juridique se trouve à l"},{"type":"text","text":"’article L.141-1 du Code de l’organisation judiciaire","marks":[{"type":"bold"}]},{"type":"text","text":" : L’État est tenu de réparer les dommages causés par un fonctionnement défectueux du service public de la justice, notamment en cas de faute lourde."}]},{"type":"paragraph","content":[{"type":"text","text":""}]},{"type":"paragraph","content":[{"type":"text","text":"À noter : la lenteur excessive de la justice relève du même fondement — "},{"type":"text","text":"obtenir une indemnisation pour le délai déraisonnable de votre procédure","marks":[{"type":"link","attrs":{"href":"/post/ma-procédure-judiciaire-n-avance-pas-puis-je-obtenir-une-indemnisation-pour-ce-délai-déraisonnable"}},{"type":"underline"}]},{"type":"text","text":" ne nécessite pas de prouver une faute lourde."}]},{"type":"paragraph","content":[{"type":"text","text":""}]},{"type":"orderedList","content":[{"type":"listItem","content":[{"type":"heading","attrs":{"level":2},"content":[{"type":"text","text":"L’exemple du féminicide de Chahinez Daoud à Mérignac"}]},{"type":"paragraph","content":[{"type":"text","text":""}]}]}]},{"type":"paragraph","content":[{"type":"text","text":"Dans l’affaire Chahinez Daoud :"}]},{"type":"paragraph","content":[{"type":"text","text":""}]},{"type":"bulletList","content":[{"type":"listItem","content":[{"type":"paragraph","content":[{"type":"text","text":"Plusieurs plaintes avaient été déposées"}]}]},{"type":"listItem","content":[{"type":"paragraph","content":[{"type":"text","text":"Des signaux de dangerosité étaient identifiés"}]}]},{"type":"listItem","content":[{"type":"paragraph","content":[{"type":"text","text":"Des mesures de contrôle n’ont pas été mises en œuvre"}]},{"type":"paragraph","content":[{"type":"text","text":""}]}]}]},{"type":"paragraph","content":[{"type":"text","text":"Les inspections administratives ont relevé une série d’erreurs et de défaillances dans le traitement du dossier."}]},{"type":"paragraph","content":[{"type":"text","text":""}]},{"type":"paragraph","content":[{"type":"text","text":"L’action engagée repose sur l’idée que "},{"type":"text","text":"le cumul de ces manquements a diminué les chances de protection et de survie de la victime","marks":[{"type":"bold"}]},{"type":"text","text":", constituant ainsi une faute lourde."}]},{"type":"paragraph","content":[{"type":"text","text":""}]},{"type":"orderedList","content":[{"type":"listItem","content":[{"type":"heading","attrs":{"level":2},"content":[{"type":"text","text":"Quelles sont les étapes pour assigner l’État ?"}]}]}]},{"type":"paragraph","content":[{"type":"text","text":""}]},{"type":"bulletList","content":[{"type":"listItem","content":[{"type":"heading","attrs":{"level":3},"content":[{"type":"text","text":" Identifier le fondement juridique"}]}]}]},{"type":"paragraph","content":[{"type":"text","text":"Il faut déterminer si l’on se situe :"}]},{"type":"paragraph","content":[{"type":"text","text":""}]},{"type":"orderedList","content":[{"type":"listItem","content":[{"type":"paragraph","content":[{"type":"text","text":"Devant le "},{"type":"text","text":"tribunal judiciaire","marks":[{"type":"bold"}]},{"type":"text","text":" (fonctionnement défectueux du service public de la justice ou de la police judiciaire)"}]}]},{"type":"listItem","content":[{"type":"paragraph","content":[{"type":"text","text":"Devant le "},{"type":"text","text":"tribunal administratif","marks":[{"type":"bold"}]},{"type":"text","text":" (autres services administratifs de l’État)"}]}]}]},{"type":"paragraph","content":[{"type":"text","text":""}]},{"type":"bulletList","content":[{"type":"listItem","content":[{"type":"heading","attrs":{"level":3},"content":[{"type":"text","text":"Rassembler les preuves"}]}]}]},{"type":"paragraph","content":[{"type":"text","text":"Le dossier doit démontrer :"}]},{"type":"paragraph","content":[{"type":"text","text":""}]},{"type":"orderedList","content":[{"type":"listItem","content":[{"type":"paragraph","content":[{"type":"text","text":"Les signalements effectués"}]}]},{"type":"listItem","content":[{"type":"paragraph","content":[{"type":"text","text":"Les décisions prises (ou non prises)"}]}]},{"type":"listItem","content":[{"type":"paragraph","content":[{"type":"text","text":"Les dysfonctionnements constatés"}]}]},{"type":"listItem","content":[{"type":"paragraph","content":[{"type":"text","text":"Le lien entre ces manquements et le préjudice subi"}]},{"type":"paragraph","content":[{"type":"text","text":""}]}]}]},{"type":"paragraph","content":[{"type":"text","text":"La preuve est centrale : la faute lourde ne se présume pas."}]},{"type":"paragraph","content":[{"type":"text","text":""}]},{"type":"bulletList","content":[{"type":"listItem","content":[{"type":"heading","attrs":{"level":3},"content":[{"type":"text","text":"Effectuer une demande préalable (selon la juridiction)"}]}]}]},{"type":"paragraph","content":[{"type":"text","text":"En matière administrative, une "},{"type":"text","text":"demande indemnitaire préalable","marks":[{"type":"bold"}]},{"type":"text","text":" est obligatoire."}]},{"type":"paragraph","content":[{"type":"text","text":""}]},{"type":"paragraph","content":[{"type":"text","text":"Devant le tribunal judiciaire, l’action peut être introduite directement par assignation."}]},{"type":"paragraph","content":[{"type":"text","text":""}]},{"type":"bulletList","content":[{"type":"listItem","content":[{"type":"heading","attrs":{"level":3},"content":[{"type":"text","text":"Assigner l’État"}]}]}]},{"type":"paragraph","content":[{"type":"text","text":"L’assignation doit exposer :"}]},{"type":"bulletList","content":[{"type":"listItem","content":[{"type":"paragraph","content":[{"type":"text","text":"Les faits"}]}]},{"type":"listItem","content":[{"type":"paragraph","content":[{"type":"text","text":"Les fautes reprochées"}]}]},{"type":"listItem","content":[{"type":"paragraph","content":[{"type":"text","text":"Le lien de causalité"}]}]},{"type":"listItem","content":[{"type":"paragraph","content":[{"type":"text","text":"Le préjudice (moral, matériel, perte de chance…)"}]}]},{"type":"listItem","content":[{"type":"paragraph","content":[{"type":"text","text":"Le montant de l’indemnisation demandée"}]}]}]},{"type":"paragraph","content":[{"type":"text","text":""}]},{"type":"orderedList","content":[{"type":"listItem","content":[{"type":"heading","attrs":{"level":2},"content":[{"type":"text","text":"Que peut-on obtenir ?"}]}]}]},{"type":"paragraph","content":[{"type":"text","text":"Le juge peut accorder :"}]},{"type":"paragraph","content":[{"type":"text","text":""}]},{"type":"bulletList","content":[{"type":"listItem","content":[{"type":"paragraph","content":[{"type":"text","text":"Des dommages et intérêts"}]}]},{"type":"listItem","content":[{"type":"paragraph","content":[{"type":"text","text":"La reconnaissance officielle des manquements"}]}]},{"type":"listItem","content":[{"type":"paragraph","content":[{"type":"text","text":"Le remboursement de frais de procédure"}]},{"type":"paragraph","content":[{"type":"text","text":""}]}]}]},{"type":"paragraph","content":[{"type":"text","text":"Au-delà de l’indemnisation, ces actions ont aussi une portée institutionnelle : elles permettent de mettre en lumière des dysfonctionnements systémiques et d’améliorer les pratiques."}]},{"type":"paragraph","content":[{"type":"text","text":""}]},{"type":"orderedList","content":[{"type":"listItem","content":[{"type":"heading","attrs":{"level":2},"content":[{"type":"text","text":"Points de vigilance"}]},{"type":"paragraph","content":[{"type":"text","text":"1. La faute lourde est difficile à caractériser"}]},{"type":"paragraph","content":[{"type":"text","text":"2. Les délais de prescription doivent être respectés"}]},{"type":"paragraph","content":[{"type":"text","text":"3. La stratégie juridique doit être rigoureuse"}]},{"type":"paragraph","content":[{"type":"text","text":""}]}]}]},{"type":"paragraph","content":[{"type":"text","text":"Ces dossiers sont complexes, tant sur le plan humain que juridique."}]},{"type":"paragraph","content":[{"type":"text","text":""}]},{"type":"paragraph","content":[{"type":"text","text":"Il est essentiel, et procéduralement obligatoire, d'être assisté d'un Cabinet d'avocats dans cette démarche."}]},{"type":"paragraph","content":[{"type":"text","text":""}]},{"type":"heading","attrs":{"level":2},"content":[{"type":"text","text":"En résumé"}]},{"type":"table","content":[{"type":"tableRow","content":[{"type":"tableCell","content":[{"type":"paragraph","content":[{"type":"text","text":"Étape"}]}]},{"type":"tableCell","content":[{"type":"paragraph","content":[{"type":"text","text":"Action"}]}]}]},{"type":"tableRow","content":[{"type":"tableCell","content":[{"type":"paragraph","content":[{"type":"text","text":"1"}]}]},{"type":"tableCell","content":[{"type":"paragraph","content":[{"type":"text","text":"Identifier la juridiction compétente"}]}]}]},{"type":"tableRow","content":[{"type":"tableCell","content":[{"type":"paragraph","content":[{"type":"text","text":"2"}]}]},{"type":"tableCell","content":[{"type":"paragraph","content":[{"type":"text","text":"Prouver un dysfonctionnement grave"}]}]}]},{"type":"tableRow","content":[{"type":"tableCell","content":[{"type":"paragraph","content":[{"type":"text","text":"3"}]}]},{"type":"tableCell","content":[{"type":"paragraph","content":[{"type":"text","text":"Démontrer le lien de causalité"}]}]}]},{"type":"tableRow","content":[{"type":"tableCell","content":[{"type":"paragraph","content":[{"type":"text","text":"4"}]}]},{"type":"tableCell","content":[{"type":"paragraph","content":[{"type":"text","text":"Chiffrer précisément le préjudice"}]}]}]},{"type":"tableRow","content":[{"type":"tableCell","content":[{"type":"paragraph","content":[{"type":"text","text":"5"}]}]},{"type":"tableCell","content":[{"type":"paragraph","content":[{"type":"text","text":"Engager l’action dans les délais"}]}]}]}]},{"type":"paragraph","content":[{"type":"text","text":"Si vous êtes confronté(e) à une situation comparable ou si vous vous interrogez sur la responsabilité de l’État dans un dossier sensible, le cabinet se tient à votre disposition pour ","marks":[{"type":"bold"}]},{"type":"text","text":"analyser votre situation et vous accompagner dans vos démarches","marks":[{"type":"bold"},{"type":"link","attrs":{"href":"https://www.jplouton-avocat.fr/honoraires-rendez-vous"}},{"type":"underline"}]},{"type":"text","text":".","marks":[{"type":"bold"}]}]}]}
